QCFx/__init__.py
QCFxPython-1.0.5.dist-info/LICENSE
QCFxPython-1.0.5.dist-info/METADATA
QCFxPython-1.0.5.dist-info/WHEEL
QCFxPython-1.0.5.dist-info/top_level.txt
QCFxPython-1.0.5.dist-info/RECORD
