Metadata-Version: 2.1
Name: QCFxPython
Version: 1.0.5
Summary: QCFx is a Python library designed to add dynamic, real-time background blurring effects to PyQt5 applications. It provides various modes of operation, allowing for different levels of quality and performance to suit the needs of your application.
Author-email: Aditya Gaur <adityagaur.home@gmail.com>
Maintainer-email: Aditya Gaur <adityagaur.home@gmail.com>
License: GNU GENERAL PUBLIC LICENSE
Project-URL: Homepage, https://github.com/xdityagr/QCFX-Python
Project-URL: Repository, https://github.com/xdityagr/QCFX-Python
Keywords: Blur Effect Library,Blurring Engine,PyQt5 Blur Effect,Windows 10 Blur Effect,Fx Engine
Classifier: Development Status :: 4 - Beta
Classifier: Programming Language :: Python
Classifier: Intended Audience :: Developers
Classifier: Topic :: Software Development :: Build Tools
Classifier: License :: OSI Approved :: GNU General Public License v3 (GPLv3)
Classifier: Programming Language :: Python :: 3
Classifier: Programming Language :: Python :: 3.6
Classifier: Programming Language :: Python :: 3.7
Classifier: Programming Language :: Python :: 3.8
Classifier: Programming Language :: Python :: 3.9
Classifier: Programming Language :: Python :: 3.10
Requires-Python: >=3.8
License-File: LICENSE
Requires-Dist: PySide2
Requires-Dist: PyQt5
Requires-Dist: pyautogui
Requires-Dist: Pillow ==9.5.0
Requires-Dist: pywin32
Requires-Dist: imagehash
